Metadata-Version: 1.1
Name: VidPlot
Version: 0.1.3
Summary: Create and Display mp4 file from matplotlib figure
Home-page: UNKNOWN
Author: Silvano Rosenau
Author-email: silvano.rosenau@studium.uni-hamburg.de
License: MIT
Keywords: video
Platform: UNKNOWN
Classifier: Development Status :: 2 - Pre-Alpha
Classifier: Intended Audience :: Education
Classifier: Operating System :: Microsoft :: Windows :: Windows 10
Classifier: License :: OSI Approved :: MIT License
Classifier: Programming Language :: Python :: 3
